helsingborgalarm/__init__.py
helsingborgalarm-1.0.1.dist-info/LICENSE
helsingborgalarm-1.0.1.dist-info/METADATA
helsingborgalarm-1.0.1.dist-info/WHEEL
helsingborgalarm-1.0.1.dist-info/top_level.txt
helsingborgalarm-1.0.1.dist-info/RECORD
